arff_csv/__init__.py
arff_csv/cli.py
arff_csv/converter.py
arff_csv/exceptions.py
arff_csv/parser.py
arff_csv/py.typed
arff_csv/writer.py
arff_csv_converter-1.1.0.dist-info/licenses/LICENSE
arff_csv_converter-1.1.0.dist-info/METADATA
arff_csv_converter-1.1.0.dist-info/WHEEL
arff_csv_converter-1.1.0.dist-info/entry_points.txt
arff_csv_converter-1.1.0.dist-info/top_level.txt
arff_csv_converter-1.1.0.dist-info/RECORD
