Metadata-Version: 2.4
Name: arff-csv-converter
Version: 1.1.0
Summary: A Python library for converting between CSV and ARFF (Weka) file formats
Author-email: Ricardo Montañana <rmontanana@gmail.com>
License-Expression: MIT
Project-URL: Homepage, https://github.com/rmontanana/arff-csv-converter
Project-URL: Documentation, https://github.com/rmontanana/arff-csv-converter#readme
Project-URL: Repository, https://github.com/rmontanana/arff-csv-converter.git
Project-URL: Bug Tracker, https://github.com/rmontanana/arff-csv-converter/issues
Project-URL: Changelog, https://github.com/rmontanana/arff-csv-converter/blob/main/CHANGELOG.md
Keywords: arff,csv,weka,converter,machine-learning,data-format,file-conversion
Classifier: Development Status :: 5 - Production/Stable
Classifier: Intended Audience :: Developers
Classifier: Intended Audience :: Science/Research
Classifier: Operating System :: OS Independent
Classifier: Programming Language :: Python :: 3
Classifier: Programming Language :: Python :: 3.11
Classifier: Programming Language :: Python :: 3.12
Classifier: Programming Language :: Python :: 3.13
Classifier: Programming Language :: Python :: 3.14
Classifier: Topic :: Scientific/Engineering :: Artificial Intelligence
Classifier: Topic :: Software Development :: Libraries :: Python Modules
Classifier: Topic :: Utilities
Classifier: Typing :: Typed
Requires-Python: >=3.11
License-File: LICENSE
Requires-Dist: pandas>=2.0.0
Requires-Dist: numpy>=1.24.0
Provides-Extra: dev
Requires-Dist: pytest>=8.0.0; extra == "dev"
Requires-Dist: pytest-cov>=6.0.0; extra == "dev"
Requires-Dist: ruff>=0.8.0; extra == "dev"
Requires-Dist: mypy>=1.13.0; extra == "dev"
Requires-Dist: pandas-stubs>=2.0.0; extra == "dev"
Requires-Dist: build>=1.0.0; extra == "dev"
Requires-Dist: twine>=5.0.0; extra == "dev"
Dynamic: license-file
